{"id":857,"slug":"andrew-frost-pretending","url":"https://www.brightonfringe.org/events/andrew-frost-pretending/","title":"Andrew Frost Pretending","company":"Andrew Frost","genre":"Cabaret & Variety","description":"Director - Tom ParryWriter, Magic Consultant - Tyler Wilson Venues:Grania Dean Studio (Lantern Theatre @ ACT) Grania Dean Studio (Lantern Theatre @ ACT) Grania Dean Studio (Lantern Theatre @ ACT)","duration_minutes":60,"age_suitability":"14+","image_url":"https://content.brightonfringe.org/wp-content/uploads/2026/03/02-26-2026-110911-8480.jpg","website":"","instagram":"https://www.instagram.com/brightonfringe/","twitter":"https://twitter.com/brightonfringe","facebook":"https://www.facebook.com/brightonfringefestival","accessibility_features":["Assistance Dog"],"content_warnings":["Audience Participation"],"cast":[],"scraped_at":"2026-05-19T08:08:29.006442","venue":{"id":3,"slug":"grania-dean-studio-lantern-theatre-act","name":"Grania Dean Studio (Lantern Theatre @ ACT)","address":"77 St James Street, East Susssex","url":"https://www.brightonfringe.org/venues/grania-dean-studio-lantern-theatre-act","lat":50.82022702785896,"lng":-0.13063054104227145},"performances":[{"id":17050,"date":"2026-05-31","time":"","standard_price":null,"concession_price":null,"is_sold_out":false,"booking_url":""},{"id":17051,"date":"2026-05-28","time":"19:00","standard_price":15.0,"concession_price":13.0,"is_sold_out":false,"booking_url":""},{"id":17052,"date":"2026-05-29","time":"19:00","standard_price":15.0,"concession_price":13.0,"is_sold_out":true,"booking_url":""},{"id":17053,"date":"2026-05-30","time":"19:00","standard_price":15.0,"concession_price":13.0,"is_sold_out":true,"booking_url":""},{"id":17054,"date":"2026-05-31","time":"19:00","standard_price":15.0,"concession_price":13.0,"is_sold_out":false,"booking_url":""}],"reviews":[{"id":215,"source_site":"Broadway Baby","reviewer":"","rating_stars":null,"rating_raw":"","excerpt":"Andrew Frost is The Greatest Card Magician in the World. Except, he isn’t, as he claims soon after he comes on stage. Yes, this lowers expectation to reasonable levels before we are given the opportunity to reach this conclusion ourselves, as he confesses that this was a quote from a random reviewer that becomes an underlying theme of the show’s narrative. But also, it immediately erodes trust and","review_url":"https://broadwaybaby.com/shows/andrew-frost-the-greatest-card-magician-in-the-world/826845"}]}