{"id":523,"slug":"are-we-nearly-dead-yet","url":"https://www.brightonfringe.org/events/are-we-nearly-dead-yet/","title":"Are We Nearly Dead Yet","company":"Outernet Productions","genre":"Cabaret & Variety","description":"This is an audacious evening's entertainment. Melancholy and irreverent psych band Crayola Lectern, masterful American satirist Will Franken, unpredictable performance artist Dave Suit and subversive musical artist Private Sector 0.333. Thanks to market forces, the Outernet brings you world-class culture in a tiny venue.","duration_minutes":240,"age_suitability":"18+","image_url":"https://d1vlmco8ur52ud.cloudfront.net/04-08-2026-191423-7352.jpg","website":"","instagram":"https://www.instagram.com/brightonfringe/","twitter":"https://twitter.com/brightonfringe","facebook":"https://www.facebook.com/brightonfringefestival","accessibility_features":["Wheelchair","Accessible","Assistance Dog"],"content_warnings":[],"cast":[],"scraped_at":"2026-05-19T09:32:12.661289","venue":{"id":86,"slug":"daltons-brighton","name":"Daltons Brighton","address":null,"url":"https://www.brightonfringe.org/venues/daltons-brighton","lat":50.8190212,"lng":-0.1343909},"performances":[{"id":25859,"date":"2026-05-31","time":"","standard_price":null,"concession_price":null,"is_sold_out":false,"booking_url":""},{"id":25860,"date":"2026-05-18","time":"20:00","standard_price":14.0,"concession_price":13.0,"is_sold_out":false,"booking_url":""}],"reviews":[]}