{"id":781,"slug":"black-brighton-market-festival-day","url":"https://www.brightonfringe.org/events/black-brighton-market-festival-day/","title":"Black Brighton Market Festival Day","company":"Black Brighton Market / flo creative","genre":"Events & Films","description":"The third Brighton Fringe edition of the popular Black Brighton Pop Up Market bringing you an exciting family-friendly day festival featuring a vibrant array of arts & craft stalls, performances, storytelling, workshops, and a cultural café - something for everyone! Addressing some of the limited opportunities for Black People/People of Colour, the pioneering Black Brighton Market venture creates a unique space for more communities have the chance to sell their art, goods and services, and to also showcase taster sessions, workshops and performances to the wider general public in the state-of-the-art Ironworks Studios. More details available on the Black Brighton Market website. All are welcome. THIS EVENT IS SPONSORED BY THE IRENE MENSAH BURSARY & FLO CREATIVE IN COLLABORATION WITH IRONWORKS STUDIOS AND THE ENTANGLED COORDINATES CO-CREATED THEATRE PRODUCTION ‘THIS IS NEW BRIGHTON’","duration_minutes":420,"age_suitability":"3+","image_url":"https://content.brightonfringe.org/wp-content/uploads/2026/03/02-11-2026-151145-8565.jpg","website":"","instagram":"https://www.instagram.com/brightonfringe/","twitter":"https://twitter.com/brightonfringe","facebook":"https://www.facebook.com/brightonfringefestival","accessibility_features":["Wheelchair","Accessible","Assistance Dog"],"content_warnings":[],"cast":[],"scraped_at":"2026-05-19T15:11:09.864377","venue":{"id":71,"slug":"ironworks-studios-studio-b","name":"Ironworks Studios (Studio B)","address":"The Ironworks 30 Cheapside, Brighton","url":"https://www.brightonfringe.org/venues/ironworks-studios-studio-b","lat":50.82923479999999,"lng":-0.138119},"performances":[{"id":33626,"date":"2026-05-31","time":"","standard_price":null,"concession_price":null,"is_sold_out":false,"booking_url":""},{"id":33627,"date":"2026-05-31","time":"12:00","standard_price":0.0,"concession_price":null,"is_sold_out":false,"booking_url":""}],"reviews":[]}