{"id":799,"slug":"cabaret-boheme","url":"https://www.brightonfringe.org/events/cabaret-boheme/","title":"Cabaret Boheme","company":"powerhouse performers Veronica Blacklace and Chris Hide, serving vocals, charisma, and pure cabaret magic. Add Purple Haze’s gravity-defying spectacle, and you’ve got a show that’s bold, brilliant, and bursting with attitude.","genre":"Cabaret & Variety","description":"Allegra Rose - Burlesque and choreorapherChris Hide - vocal powerhouse and musical directorPurple Haze- aerialistDave the bear - The one everyone wants! BoylesqueVeronica Blacklace - The creator and everything else","duration_minutes":120,"age_suitability":"18+","image_url":"https://content.brightonfringe.org/wp-content/uploads/2026/03/02-26-2026-115854-6970.jpg","website":"","instagram":"https://www.instagram.com/brightonfringe/","twitter":"https://twitter.com/brightonfringe","facebook":"https://www.facebook.com/brightonfringefestival","accessibility_features":["Wheelchair","Accessible","Assistance Dog"],"content_warnings":["Semi nudity","Haze","Nudity"],"cast":[],"scraped_at":"2026-05-19T08:08:19.176836","venue":{"id":79,"slug":"sabai-pavilion","name":"Sabai Pavilion","address":"Preston Park, Preston Road, East Sussex","url":"https://www.brightonfringe.org/venues/sabai-pavilion","lat":50.83987701737032,"lng":-0.14608383178710938},"performances":[{"id":16733,"date":"2026-05-31","time":"","standard_price":null,"concession_price":null,"is_sold_out":false,"booking_url":""},{"id":16734,"date":"2026-05-24","time":"21:00","standard_price":17.0,"concession_price":null,"is_sold_out":false,"booking_url":""}],"reviews":[]}