{"id":746,"slug":"cest-magnifique","url":"https://www.brightonfringe.org/events/cest-magnifique/","title":"Cest Magnifique","company":"Chocolate Box Theatre","genre":"Cabaret & Variety","description":"Set to take cabaret to new heights with a special performance on Brighton's i360! C’est Magnifique, winners of the 2025 Fringe Outgoing Touring Award and brought to you by Chocolate Box Theatre, is escapist heaven for any musical theatre fan. Step back to an imagined cabaret haunt in 1930s Paris or Berlin and join Cyril the emcee with Gaylord, Babette, Goldie, Bert and the indomitable Zelda as they perform ballads, torch songs, comedy numbers, musical theatre favourites and a pop of pop. C’est Magnifique appears in the Wunderbarn for four fabulous nights, plus a very special C’est Magnifique in the Sky aboard the iconic Brighton i360. Performed high above the seafront, it promises sparkle, sophistication and sky-high entertainment. Selling out to packed audiences with rave reviews, they don’t just can-can , they will, will; accompanied by live music and (very) high kicks!","duration_minutes":60,"age_suitability":"18+","image_url":"https://content.brightonfringe.org/wp-content/uploads/2026/03/02-03-2026-102518-1019.jpg","website":"","instagram":"https://www.instagram.com/brightonfringe/","twitter":"https://twitter.com/brightonfringe","facebook":"https://www.facebook.com/brightonfringefestival","accessibility_features":["Wheelchair","Accessible","Assistance Dog"],"content_warnings":["Haze/Smoke Effects","Haze","Smoke"],"cast":[],"scraped_at":"2026-05-19T15:11:06.266197","venue":{"id":91,"slug":"the-pod-brighton-i360","name":"The Pod - Brighton i360","address":"Lower Kings Road, East Sussex","url":"https://www.brightonfringe.org/venues/the-pod-brighton-i360","lat":50.821377190513005,"lng":-0.15091180801391602},"performances":[{"id":33509,"date":"2026-05-31","time":"","standard_price":null,"concession_price":null,"is_sold_out":false,"booking_url":""},{"id":33510,"date":"2026-05-09","time":"20:45","standard_price":15.0,"concession_price":12.0,"is_sold_out":true,"booking_url":""},{"id":33511,"date":"2026-05-14","time":"20:30","standard_price":25.0,"concession_price":20.0,"is_sold_out":false,"booking_url":""},{"id":33512,"date":"2026-05-29","time":"20:45","standard_price":15.0,"concession_price":12.0,"is_sold_out":false,"booking_url":""}],"reviews":[]}