{"id":106,"slug":"crazy-rabbit-ladies","url":"https://www.brightonfringe.org/events/crazy-rabbit-ladies/","title":"Crazy Rabbit Ladies","company":"Quinn and Madden Enterprises","genre":"Comedy","description":"","duration_minutes":60,"age_suitability":"18+","image_url":"https://content.brightonfringe.org/wp-content/uploads/2026/03/01-10-2026-203147-8839.jpg","website":"","instagram":"https://www.instagram.com/brightonfringe/","twitter":"https://twitter.com/brightonfringe","facebook":"https://www.facebook.com/brightonfringefestival","accessibility_features":["Accessible","Assistance Dog"],"content_warnings":["rabbit related material"],"cast":[],"scraped_at":"2026-05-19T08:06:20.835018","venue":{"id":15,"slug":"presuming-ed","name":"Presuming Ed","address":null,"url":"https://www.brightonfringe.org/venues/presuming-ed","lat":50.8309813,"lng":-0.1360435},"performances":[{"id":14097,"date":"2026-05-31","time":"","standard_price":null,"concession_price":null,"is_sold_out":false,"booking_url":""},{"id":14098,"date":"2026-05-30","time":"17:15","standard_price":0.0,"concession_price":null,"is_sold_out":false,"booking_url":""}],"reviews":[]}