{"id":640,"slug":"humdinger-words-for-whippersnappers-and-guttersnipes","url":"https://www.brightonfringe.org/events/humdinger-words-for-whippersnappers-and-guttersnipes/","title":"Humdinger Words For Whippersnappers And Guttersnipes","company":"Ben Dali","genre":"Children & Young People","description":"Step into the poetic classroom of the UK's most entertaining supply teacher, as he welcomes you into a world of witty wordplay, tantalising trivia, megaLOLs and even rhyming magic! Humdinger Words for Whippersnappers and Guttersnipes is a PG hour of comedy-cabaret poetry led by stage hypnotist turned teacher, Ben Dali. Presented as a school day, this is a fast-paced journey through elements of the KS2 and KS3 curriculum. 'Mr Dali' combines poetry, comedy and insights into his eclectic background to deliver epic poems he wrote aged 7, a balloon-modelling tutorial poem, a joyful exploration of English's finest 'Humdinger Words', and genuine improvised rhyming mind reading. Designed for intellectually curious and creative 7–14 year-olds, the whole family will leave entertained, educated and inspired. The show includes a supportive Show-and-Tell segment, where children are invited to perform their own poems. So, budding young wordsmiths desirous of a platform: come prepared to share.","duration_minutes":60,"age_suitability":"7+","image_url":"https://content.brightonfringe.org/wp-content/uploads/2026/03/02-08-2026-182331-6436.jpg","website":"","instagram":"https://www.instagram.com/brightonfringe/","twitter":"https://twitter.com/brightonfringe","facebook":"https://www.facebook.com/brightonfringefestival","accessibility_features":["Wheelchair","Accessible","Assistance Dog"],"content_warnings":[],"cast":[],"scraped_at":"2026-05-19T15:10:50.499776","venue":{"id":46,"slug":"rotunda-theatre-brighton-pip","name":"Rotunda Theatre Brighton: Pip","address":"Regency Square, England","url":"https://www.brightonfringe.org/venues/rotunda-theatre-brighton-pip","lat":50.82255917916854,"lng":-0.1504214084941835},"performances":[{"id":33069,"date":"2026-05-31","time":"","standard_price":null,"concession_price":null,"is_sold_out":false,"booking_url":""},{"id":33070,"date":"2026-05-09","time":"11:30","standard_price":10.0,"concession_price":8.0,"is_sold_out":false,"booking_url":""},{"id":33071,"date":"2026-05-10","time":"11:30","standard_price":10.0,"concession_price":8.0,"is_sold_out":false,"booking_url":""}],"reviews":[]}