{"id":517,"slug":"kahloca","url":"https://www.brightonfringe.org/events/kahloca/","title":"Kahloca","company":"WomanEwer","genre":"Circus Dance & Physical Theatre","description":"KAH’LOCA is a 20 minutes family friendly outdoor work. Women dressed in bright colours with flamboyant funky headpieces use dance-theatre to challenge the narrative of what it means to be a woman and bring to public attention the scale of violence against women. KAH’LOCA's costumes symbolise a desire for everyone to have their own voice, to speak out, be bold and step up for themselves, empowering the harmed and shaping once mute spaces. A combination of voices, classical guitar song, gritty percussive sounds and protests creates the overall soundscape, overlapping with the breath of the dancers in motion to create a multi-sensory live performance which celebrates female strength and resilience.","duration_minutes":20,"age_suitability":"3+","image_url":"https://d1vlmco8ur52ud.cloudfront.net/03-29-2026-215221-7433.jpg","website":"","instagram":"https://www.instagram.com/brightonfringe/","twitter":"https://twitter.com/brightonfringe","facebook":"https://www.facebook.com/brightonfringefestival","accessibility_features":["Wheelchair","Accessible","Assistance Dog"],"content_warnings":["Haze/Smoke Effects","Haze","Smoke","Loud","Violence"],"cast":[],"scraped_at":"2026-05-19T09:32:11.268507","venue":{"id":24,"slug":"jubilee-square","name":"Jubilee Square","address":null,"url":"https://www.brightonfringe.org/venues/jubilee-square","lat":50.8247844,"lng":-0.1384238},"performances":[{"id":25911,"date":"2026-05-31","time":"","standard_price":null,"concession_price":null,"is_sold_out":false,"booking_url":""},{"id":25912,"date":"2026-05-10","time":"11:00","standard_price":0.0,"concession_price":null,"is_sold_out":false,"booking_url":""},{"id":25913,"date":"2026-05-10","time":"13:00","standard_price":0.0,"concession_price":null,"is_sold_out":false,"booking_url":""},{"id":25914,"date":"2026-05-10","time":"15:00","standard_price":0.0,"concession_price":null,"is_sold_out":false,"booking_url":""},{"id":25915,"date":"2026-05-10","time":"17:00","standard_price":0.0,"concession_price":null,"is_sold_out":false,"booking_url":""}],"reviews":[]}