{"id":578,"slug":"sarah-roberts-scary-movie-7-work-in-progress","url":"https://www.brightonfringe.org/events/sarah-roberts-scary-movie-7-work-in-progress/","title":"Sarah Roberts Scary Movie 7 Work In Progress","company":"Sarah Roberts","genre":"Comedy","description":"Venues:Laughing Horse @ Caroline of Brunswick","duration_minutes":60,"age_suitability":"18+","image_url":"https://content.brightonfringe.org/wp-content/uploads/2026/03/12-18-2025-162237-7344.jpg","website":"","instagram":"https://www.instagram.com/brightonfringe/","twitter":"https://twitter.com/brightonfringe","facebook":"https://www.facebook.com/brightonfringefestival","accessibility_features":["Assistance Dog"],"content_warnings":[],"cast":[],"scraped_at":"2026-05-19T08:07:42.397458","venue":{"id":90,"slug":"laughing-horse-caroline-of-brunswick","name":"Laughing Horse @ Caroline of Brunswick","address":"39 Ditchling Road, East Sussex","url":"https://www.brightonfringe.org/venues/laughing-horse-caroline-of-brunswick","lat":50.830641573421445,"lng":-0.13459861278533936},"performances":[{"id":15880,"date":"2026-05-31","time":"","standard_price":null,"concession_price":null,"is_sold_out":false,"booking_url":""},{"id":15881,"date":"2026-05-21","time":"21:30","standard_price":8.0,"concession_price":null,"is_sold_out":false,"booking_url":""}],"reviews":[]}