{"id":372,"slug":"severe-lacerations-to-head","url":"https://www.brightonfringe.org/events/severe-lacerations-to-head/","title":"Severe Lacerations To Head","company":"Kate Smurthwaite","genre":"Comedy","description":"This is all a bit f*cked. We should talk. A new hour from Kate on the state of the world and the world of the state. To be clear about the title... This is a show about genocide and fascism. The stuff about traumatic brain injury is there for light relief. “Kate is a countercultural force of nature, a scourge of the right and a very clever woman... I undeservedly recommend going to see any of [her shows]. You won’t be disappointed.” (Morning Star)","duration_minutes":60,"age_suitability":"18+","image_url":"https://content.brightonfringe.org/wp-content/uploads/2025/12/10-28-2025-215941-8311.jpg","website":"","instagram":"https://www.instagram.com/brightonfringe/","twitter":"https://twitter.com/brightonfringe","facebook":"https://www.facebook.com/brightonfringefestival","accessibility_features":["Assistance Dog"],"content_warnings":["We are going to talk about capitalism","Violence"],"cast":[],"scraped_at":"2026-05-19T15:10:12.559847","venue":{"id":17,"slug":"comedy-at-the-caxton","name":"Comedy at the Caxton","address":"36 North Gardens, East Sussex","url":"https://www.brightonfringe.org/venues/comedy-at-the-caxton","lat":50.826791599999986,"lng":-0.14253597354126013},"performances":[{"id":32081,"date":"2026-05-31","time":"","standard_price":null,"concession_price":null,"is_sold_out":false,"booking_url":""},{"id":32082,"date":"2026-05-08","time":"20:30","standard_price":10.0,"concession_price":8.0,"is_sold_out":false,"booking_url":""},{"id":32083,"date":"2026-05-09","time":"20:30","standard_price":10.0,"concession_price":8.0,"is_sold_out":false,"booking_url":""}],"reviews":[]}