{"id":397,"slug":"soapbox-science-brighton","url":"https://www.brightonfringe.org/events/soapbox-science-brighton/","title":"Soapbox Science Brighton","company":"Soapbox Science Brighton","genre":"Events & Films","description":"Twelve women and non-binary scientists will be bringing their research discoveries to the seaside. Join this informal event for demonstrations and discussions while enjoying the sun, the sea and the amazing female-led research taking place in our region!","duration_minutes":180,"age_suitability":"0+","image_url":"https://content.brightonfringe.org/wp-content/uploads/2026/03/03-09-2026-115132-7845.jpg","website":"","instagram":"https://www.instagram.com/brightonfringe/","twitter":"https://twitter.com/brightonfringe","facebook":"https://www.facebook.com/brightonfringefestival","accessibility_features":[],"content_warnings":[],"cast":[],"scraped_at":"2026-05-19T09:31:56.268070","venue":{"id":73,"slug":"i360-event-space-east","name":"i360 Event Space East","address":null,"url":"https://www.brightonfringe.org/venues/i360-event-space-east","lat":50.8210725572507,"lng":-0.14934323650587444},"performances":[{"id":25371,"date":"2026-05-31","time":"","standard_price":null,"concession_price":null,"is_sold_out":false,"booking_url":""},{"id":25372,"date":"2026-05-30","time":"11:00","standard_price":0.0,"concession_price":null,"is_sold_out":false,"booking_url":""}],"reviews":[]}